autodiff/__init__.py
autodiff/node.py
autodiff/operators.py
autodiff/utils.py
autodiff/visualization.py
autodiff_jel-0.0.1.dist-info/LICENSE
autodiff_jel-0.0.1.dist-info/METADATA
autodiff_jel-0.0.1.dist-info/WHEEL
autodiff_jel-0.0.1.dist-info/top_level.txt
autodiff_jel-0.0.1.dist-info/RECORD
