Metadata-Version: 2.1
Name: autodiff-jel
Version: 0.0.1
Summary: Python library for Automatic Differentiation
Home-page: https://github.com/teamjel/cs207-FinalProject
Author: Team JEL
Author-email: 
License: UNKNOWN
Platform: UNKNOWN
Classifier: Programming Language :: Python :: 3
Classifier: License :: OSI Approved :: MIT License
Classifier: Operating System :: OS Independent
